{
  "items": [
    {
      "type": "item",
      "title": "Introduction",
      "uri": "docs/Introduction.md"
    },  
    {
      "type": "item",
      "title": "Getting Started",
      "uri": "docs/Getting-Started.md"
    },
    {
      "type": "divider",
      "title": "SDK"
    },
    {
      "type": "item",
      "title": "Javascript",
      "uri": "docs/SDK/Javascript.md"
    },  
    {
      "type": "divider",
      "title": "API (internal)"
    },
    {
      "type": "item",
      "title": "API Reference",
      "uri": "reference/Playback-API.yaml"
    }
  ]
}
